README.txt
setup.cfg
setup.py
Products/__init__.py
Products.ARFilePreview.egg-info/PKG-INFO
Products.ARFilePreview.egg-info/SOURCES.txt
Products.ARFilePreview.egg-info/dependency_links.txt
Products.ARFilePreview.egg-info/entry_points.txt
Products.ARFilePreview.egg-info/namespace_packages.txt
Products.ARFilePreview.egg-info/not-zip-safe
Products.ARFilePreview.egg-info/paster_plugins.txt
Products.ARFilePreview.egg-info/requires.txt
Products.ARFilePreview.egg-info/top_level.txt
Products/ARFilePreview/__init__.py
Products/ARFilePreview/adapters.py
Products/ARFilePreview/config.py
Products/ARFilePreview/configure.zcml
Products/ARFilePreview/events.py
Products/ARFilePreview/interfaces.py
Products/ARFilePreview/views.py
Products/ARFilePreview/Extensions/Install.py
Products/ARFilePreview/Extensions/__init__.py
Products/ARFilePreview/i18n/arfilepreview-plone-en.po
Products/ARFilePreview/i18n/arfilepreview-plone-fr.po
Products/ARFilePreview/templates/file_asdoc.pt
Products/ARFilePreview/templates/file_preview.pt
Products/ARFilePreview/templates/fullview.pt
docs/HISTORY.txt
docs/INSTALL.txt
docs/LICENSE.GPL
docs/LICENSE.txt