Metadata-Version: 1.0
Name: Products.ARFilePreview
Version: 2.2.2
Summary: UNKNOWN
Home-page: http://www.atreal.net/
Author: atReal
Author-email: mailto:contact@atreal.net
License: GPL
Platform: UNKNOWN
Classifier: Framework :: Plone
Classifier: Programming Language :: Python
Classifier: Topic :: Software Development :: Libraries :: Python Modules
